AircvLibrary/AircvLibrary.py
AircvLibrary/__init__.py
robotframework_aircvlibrary-1.0.2.dist-info/top_level.txt
robotframework_aircvlibrary-1.0.2.dist-info/pbr.json
robotframework_aircvlibrary-1.0.2.dist-info/METADATA
robotframework_aircvlibrary-1.0.2.dist-info/DESCRIPTION.rst
robotframework_aircvlibrary-1.0.2.dist-info/metadata.json
robotframework_aircvlibrary-1.0.2.dist-info/WHEEL
robotframework_aircvlibrary-1.0.2.dist-info/RECORD
