Metadata-Version: 2.0
Name: robotframework-aircvlibrary
Version: 1.0.2
Summary: aircv wrapper for RobotFramework
Home-page: https://github.com/Netease-AutoTest/robotframework-aircvlibrary
Author: Joe Hisaishi
Author-email: joehisaishi1943@gmail.com
License: GPLv2
Platform: UNKNOWN
Classifier: Environment :: Console
Classifier: Intended Audience :: Developers
Classifier: Operating System :: OS Independent
Classifier: Programming Language :: Python :: 2.7
Requires-Dist: aircv (>=1.4.4)
Requires-Dist: robotframework (>=2.9.2)
